jaiminho/__init__.py
jaiminho/exchange.py
jaiminho-0.0.8.dist-info/LICENSE
jaiminho-0.0.8.dist-info/METADATA
jaiminho-0.0.8.dist-info/WHEEL
jaiminho-0.0.8.dist-info/top_level.txt
jaiminho-0.0.8.dist-info/RECORD
