Metadata-Version: 2.1
Name: jaiminho
Version: 0.0.8
Summary: Solução de gerenciamento e envio de e-mails
Home-page: https://github.com/ThiagoPanini/jaiminho
Author: Thiago Panini
Author-email: thipanini94@gmail.com
License: MIT
Keywords: Mail,Microsoft Exchange,exchangelib,HTML mail
Platform: UNKNOWN
Classifier: Programming Language :: Python :: 3
Classifier: Development Status :: 3 - Alpha
Classifier: Environment :: Console
Classifier: Framework :: Jupyter
Classifier: Intended Audience :: Developers
Classifier: Natural Language :: Portuguese (Brazilian)
Classifier: License :: OSI Approved :: MIT License
Classifier: Operating System :: OS Independent
Classifier: Programming Language :: Python :: 3.6
Classifier: Programming Language :: Python :: 3.7
Classifier: Programming Language :: Python :: 3.8
Classifier: Programming Language :: Python :: 3.9
Classifier: Topic :: Software Development :: Libraries :: Python Modules
Requires-Python: >=3.0.0
License-File: LICENSE
Requires-Dist: exchangelib (<=4.5.0)
Requires-Dist: pandas
Requires-Dist: pretty-html-table
Requires-Dist: tzlocal (==3.0)
